LICENSE.txt
README.md
setup.py
cim_optimizer/AHC.py
cim_optimizer/AHC_tuning.py
cim_optimizer/CAC.py
cim_optimizer/CAC_tuning.py
cim_optimizer/CIM_helper.py
cim_optimizer/__init__.py
cim_optimizer/extAHC.py
cim_optimizer/extAHC_tuning.py
cim_optimizer/optimal_params.py
cim_optimizer/setup.py
cim_optimizer/solve_Ising.py
cim_optimizer.egg-info/PKG-INFO
cim_optimizer.egg-info/SOURCES.txt
cim_optimizer.egg-info/dependency_links.txt
cim_optimizer.egg-info/requires.txt
cim_optimizer.egg-info/top_level.txt