Metadata-Version: 2.1
Name: cim-optimizer
Version: 1.0.3
Summary: Simulated Implementation of the Coherent Ising Machine
Home-page: https://github.com/mcmahon-lab/cim-optimizer
Author: McMahon Lab
Author-email: pmcmahon@cornell.edu
License: CC-BY-4.0 license
Classifier: Development Status :: 3 - Alpha
Classifier: Programming Language :: Python :: 3.7
Classifier: Programming Language :: Python :: 3.8
Classifier: Programming Language :: Python :: 3.9
Classifier: Programming Language :: Python :: 3.10
Requires-Python: >=3.7
License-File: LICENSE.txt
